LICENSE.txt
README.md
bpasslh/__init__.py
bpasslh/data/act.csv
bpasslh/data/nsw.csv
bpasslh/data/nt.csv
bpasslh/data/nz.csv
bpasslh/data/qld.csv
bpasslh/data/sa.csv
bpasslh/data/shapefiles/PSMA/README.md
bpasslh/data/shapefiles/PSMA/act/ACT_STATE_POLYGON_shp.dbf
bpasslh/data/shapefiles/PSMA/act/ACT_STATE_POLYGON_shp.prj
bpasslh/data/shapefiles/PSMA/act/ACT_STATE_POLYGON_shp.qpj
bpasslh/data/shapefiles/PSMA/act/ACT_STATE_POLYGON_shp.shp
bpasslh/data/shapefiles/PSMA/act/ACT_STATE_POLYGON_shp.shx
bpasslh/data/shapefiles/PSMA/nsw/NSW_STATE_POLYGON_shp.dbf
bpasslh/data/shapefiles/PSMA/nsw/NSW_STATE_POLYGON_shp.prj
bpasslh/data/shapefiles/PSMA/nsw/NSW_STATE_POLYGON_shp.qpj
bpasslh/data/shapefiles/PSMA/nsw/NSW_STATE_POLYGON_shp.shp
bpasslh/data/shapefiles/PSMA/nsw/NSW_STATE_POLYGON_shp.shx
bpasslh/data/shapefiles/PSMA/nt/NT_STATE_POLYGON_shp.dbf
bpasslh/data/shapefiles/PSMA/nt/NT_STATE_POLYGON_shp.prj
bpasslh/data/shapefiles/PSMA/nt/NT_STATE_POLYGON_shp.qpj
bpasslh/data/shapefiles/PSMA/nt/NT_STATE_POLYGON_shp.shp
bpasslh/data/shapefiles/PSMA/nt/NT_STATE_POLYGON_shp.shx
bpasslh/data/shapefiles/PSMA/ot/OT_STATE_POLYGON_shp.dbf
bpasslh/data/shapefiles/PSMA/ot/OT_STATE_POLYGON_shp.prj
bpasslh/data/shapefiles/PSMA/ot/OT_STATE_POLYGON_shp.qpj
bpasslh/data/shapefiles/PSMA/ot/OT_STATE_POLYGON_shp.shp
bpasslh/data/shapefiles/PSMA/ot/OT_STATE_POLYGON_shp.shx
bpasslh/data/shapefiles/PSMA/qld/QLD_STATE_POLYGON_shp.dbf
bpasslh/data/shapefiles/PSMA/qld/QLD_STATE_POLYGON_shp.prj
bpasslh/data/shapefiles/PSMA/qld/QLD_STATE_POLYGON_shp.shp
bpasslh/data/shapefiles/PSMA/qld/QLD_STATE_POLYGON_shp.shx
bpasslh/data/shapefiles/PSMA/sa/SA_STATE_POLYGON_shp.dbf
bpasslh/data/shapefiles/PSMA/sa/SA_STATE_POLYGON_shp.prj
bpasslh/data/shapefiles/PSMA/sa/SA_STATE_POLYGON_shp.qpj
bpasslh/data/shapefiles/PSMA/sa/SA_STATE_POLYGON_shp.shp
bpasslh/data/shapefiles/PSMA/sa/SA_STATE_POLYGON_shp.shx
bpasslh/data/shapefiles/PSMA/tas/TAS_STATE_POLYGON_shp.dbf
bpasslh-2.1.1.dist-info/LICENSE.txt
bpasslh-2.1.1.dist-info/WHEEL
bpasslh-2.1.1.dist-info/METADATA
bpasslh-2.1.1.dist-info/RECORD
