Metadata-Version: 2.1
Name: bpasslh
Version: 2.1.1
Summary: Location generalisation for sensitive species
Author: Grahame Bowland
Author-email: grahame.bowland@qcif.edu.au
Requires-Python: >=3.6
Classifier: Programming Language :: Python :: 3
Classifier: Programming Language :: Python :: 3.6
Classifier: Programming Language :: Python :: 3.7
Classifier: Programming Language :: Python :: 3.8
Requires-Dist: fiona (>=1.8.13,<2.0.0)
Requires-Dist: requests (>=2.23.0,<3.0.0)
Requires-Dist: shapely (>=1.7.0,<2.0.0)
